ChangeLog
LICENSE
MANIFEST.in
README.md
cdmpyparser.py
cdmpyparserversion.py
setup.py
cdmpyparser.egg-info/PKG-INFO
cdmpyparser.egg-info/SOURCES.txt
cdmpyparser.egg-info/dependency_links.txt
cdmpyparser.egg-info/top_level.txt
src/cdmpyparser.c
tests/annot.ok
tests/annot.py
tests/class_defs.ok
tests/class_defs.py
tests/class_members.ok
tests/class_members.py
tests/coding1.ok
tests/coding1.py
tests/coding2.ok
tests/coding2.py
tests/coding3.ok
tests/coding3.py
tests/commentsonly.ok
tests/commentsonly.py
tests/decorators.ok
tests/decorators.py
tests/docstring.ok
tests/docstring.py
tests/docstring2.ok
tests/docstring2.py
tests/docstring3.ok
tests/docstring3.py
tests/empty.ok
tests/empty.py
tests/empty_brackets.ok
tests/empty_brackets.py
tests/errors.ok
tests/errors.py
tests/func_defs.ok
tests/func_defs.py
tests/globals.ok
tests/globals.py
tests/import.ok
tests/import.py
tests/lexererror.py
tests/loneimport.py
tests/nested_classes.ok
tests/nested_classes.py
tests/nested_funcs.ok
tests/nested_funcs.py
tests/noendofline.ok
tests/noendofline.py
tests/one_comment.ok
tests/one_comment.py
tests/print.py
tests/print2.py
tests/static_members.ok
tests/static_members.py
tests/ut.py
tests/wrong_indent.ok
tests/wrong_indent.py
tests/wrong_stop.ok
tests/wrong_stop.py