Metadata-Version: 1.2
Name: cdmpyparser
Version: 3.3.2
Summary: Fast and comprehensive Python language parser. Written as a part of the Codimension project, this parser aims at pulling the most data from Python sources while exceeding the speed of existing parsers.
Home-page: https://github.com/SergeySatskiy/cdm-pythonparser
Author: Sergey Satskiy
Author-email: sergey.satskiy@gmail.com
License: GPLv3
Platform: any
Classifier: Development Status :: 5 - Production/Stable
Classifier: Intended Audience :: Developers
Classifier: License :: OSI Approved :: GNU General Public License (GPL)
Classifier: Operating System :: POSIX :: Linux
Classifier: Programming Language :: C
Classifier: Programming Language :: Python :: 3
Classifier: Topic :: Software Development :: Libraries :: Python Modules
Requires-Python: >=3.5, <3.10
